iterlite/__init__.py
iterlite/enumerable.py
rustlite/__init__.py
rustlite/enumerable.py
rustlite_iter/__init__.py
rustlite_iter/enumerable.py
rustlite_iter/test.py
iterlite-0.2.2.dist-info/METADATA
iterlite-0.2.2.dist-info/WHEEL
iterlite-0.2.2.dist-info/top_level.txt
iterlite-0.2.2.dist-info/RECORD
