Metadata-Version: 2.1
Name: iterlite
Version: 0.2.2
Summary: rust like iterators for python
Home-page: https://github.com/peturparkur/python-rustlite
Author: Peter Nagymathe
Author-email: peter@nagymathe.xyz
License: AGPLv3+
Classifier: Programming Language :: Python :: 3.10
Classifier: Programming Language :: Python :: 3 :: Only
Classifier: Topic :: Software Development :: Libraries :: Python Modules
Classifier: Typing :: Typed
